src/__init__.py
src/date.py
nepdate-0.0.4.dist-info/METADATA
nepdate-0.0.4.dist-info/WHEEL
nepdate-0.0.4.dist-info/entry_points.txt
nepdate-0.0.4.dist-info/top_level.txt
nepdate-0.0.4.dist-info/RECORD
