Metadata-Version: 2.1
Name: nepdate
Version: 0.0.4
Summary: Gets today's nepali date
Home-page: UNKNOWN
Author: Samir Maharjan  
Author-email: Samir84753@gmail.com
License: UNKNOWN
Keywords: nepalidate,date
Platform: UNKNOWN
Classifier: Development Status :: 1 - Planning
Classifier: Intended Audience :: Developers
Classifier: Programming Language :: Python :: 3
Classifier: Operating System :: Unix
Classifier: Operating System :: MacOS :: MacOS X
Classifier: Operating System :: Microsoft :: Windows
Requires-Dist: beautifulsoup4 (==4.10.0)
Requires-Dist: bs4 (==0.0.1)
Requires-Dist: certifi (==2021.5.30)
Requires-Dist: charset-normalizer (==2.0.6)
Requires-Dist: idna (==3.2)
Requires-Dist: requests (==2.26.0)
Requires-Dist: soupsieve (==2.2.1)
Requires-Dist: urllib3 (==1.26.6)
